__init__.py
autofinetune.py
AutoFineTune-0.0.0.dist-info/LICENSE
AutoFineTune-0.0.0.dist-info/METADATA
AutoFineTune-0.0.0.dist-info/WHEEL
AutoFineTune-0.0.0.dist-info/top_level.txt
AutoFineTune-0.0.0.dist-info/RECORD
