Metadata-Version: 2.1
Name: AutoFineTune
Version: 0.0.0
Summary: AutoFineTune: How to Finetune Pretrained Models
Author-email: Ivo Rapant <rapantios@gmail.com>
License: BSD 3-Clause License
Classifier: Development Status :: 3 - Alpha
Classifier: Programming Language :: Python :: 3
Classifier: License :: OSI Approved :: BSD License
Classifier: Operating System :: OS Independent
Requires-Python: >=3.10
License-File: LICENSE
